setup.py
bin/slicer-indexer
cubes_search/__init__.py
cubes_search/base.py
cubes_search/sphinx.py
cubes_search/sphinxapi.py
cubes_search/whoosh_engine.py
cubes_search.egg-info/PKG-INFO
cubes_search.egg-info/SOURCES.txt
cubes_search.egg-info/dependency_links.txt
cubes_search.egg-info/top_level.txt