Metadata-Version: 1.1
Name: cubes-search
Version: 0.3.0
Summary: Search backend for Cubes
Home-page: http://databrewery.org
Author: Stefan Urbanek
Author-email: stefan.urbanek@gmail.com
License: MIT
Keywords: olap multidimensional data analysis
Platform: UNKNOWN
Classifier: Development Status :: 4 - Beta
Classifier: Intended Audience :: Developers
Classifier: Intended Audience :: Science/Research
Classifier: License :: OSI Approved :: GNU General Public License (GPL)
Classifier: Programming Language :: Python
Classifier: Topic :: Database
Classifier: Topic :: Scientific/Engineering
Classifier: Topic :: Utilities
